yafowil-3.1.1-py3.11-nspkg.pth
yafowil/base.py
yafowil/button.py
yafowil/checkbox.py
yafowil/common.py
yafowil/compat.py
yafowil/compound.py
yafowil/controller.py
yafowil/datatypes.py
yafowil/email.py
yafowil/example.py
yafowil/field.py
yafowil/file.py
yafowil/hidden.py
yafowil/lines.py
yafowil/loader.py
yafowil/number.py
yafowil/password.py
yafowil/persistence.py
yafowil/proxy.py
yafowil/resources.py
yafowil/search.py
yafowil/select.py
yafowil/table.py
yafowil/tag.py
yafowil/text.py
yafowil/textarea.py
yafowil/tsf.py
yafowil/url.py
yafowil/utils.py
yafowil/i18n/__init__.py
yafowil/i18n/locales/yafowil.pot
yafowil/i18n/locales/de/LC_MESSAGES/yafowil.mo
yafowil/i18n/locales/de/LC_MESSAGES/yafowil.po
yafowil/i18n/locales/en/LC_MESSAGES/yafowil.mo
yafowil/i18n/locales/en/LC_MESSAGES/yafowil.po
yafowil/tests/__init__.py
yafowil/tests/test_base.py
yafowil/tests/test_button.py
yafowil/tests/test_checkbox.py
yafowil/tests/test_common.py
yafowil/tests/test_compound.py
yafowil/tests/test_controller.py
yafowil/tests/test_datatypes.py
yafowil/tests/test_email.py
yafowil/tests/test_field.py
yafowil/tests/test_file.py
yafowil/tests/test_hidden.py
yafowil/tests/test_lines.py
yafowil/tests/test_number.py
yafowil/tests/test_password.py
yafowil/tests/test_persistence.py
yafowil/tests/test_proxy.py
yafowil/tests/test_resources.py
yafowil/tests/test_search.py
yafowil/tests/test_select.py
yafowil/tests/test_table.py
yafowil/tests/test_tag.py
yafowil/tests/test_text.py
yafowil/tests/test_textarea.py
yafowil/tests/test_tsf.py
yafowil/tests/test_url.py
yafowil/tests/test_utils.py
yafowil-3.1.1.dist-info/LICENSE.rst
yafowil-3.1.1.dist-info/METADATA
yafowil-3.1.1.dist-info/WHEEL
yafowil-3.1.1.dist-info/entry_points.txt
yafowil-3.1.1.dist-info/namespace_packages.txt
yafowil-3.1.1.dist-info/top_level.txt
yafowil-3.1.1.dist-info/RECORD
