Metadata-Version: 2.1
Name: yafowil
Version: 3.1.1
Summary: YAFOWIL - declarative, framework independent, flexible HTML forms
Home-page: http://github.com/conestack/yafowil
Author: Yafowil Contributors
Author-email: dev@conestack.org
License: Simplified BSD
Keywords: html form rendering processing
Classifier: Development Status :: 5 - Production/Stable
Classifier: License :: OSI Approved :: BSD License
Classifier: Intended Audience :: Developers
Classifier: Topic :: Software Development
Classifier: Topic :: Internet :: WWW/HTTP :: Dynamic Content
Classifier: Operating System :: OS Independent
Classifier: Programming Language :: Python
Classifier: Programming Language :: Python :: 2.7
Classifier: Programming Language :: Python :: 3.7
Classifier: Programming Language :: Python :: 3.8
Classifier: Programming Language :: Python :: 3.9
Classifier: Programming Language :: Python :: 3.10
License-File: LICENSE.rst
Requires-Dist: node>=1.2
Requires-Dist: setuptools
Requires-Dist: webresource
Provides-Extra: test
Requires-Dist: coverage; extra == "test"
Requires-Dist: lxml; extra == "test"
Requires-Dist: pytest; extra == "test"
